arikaim/client/apiresponse.py
arikaim/client/client.py
arikaim_client-1.0.8.dist-info/LICENSE.txt
arikaim_client-1.0.8.dist-info/METADATA
arikaim_client-1.0.8.dist-info/WHEEL
arikaim_client-1.0.8.dist-info/top_level.txt
arikaim_client-1.0.8.dist-info/RECORD
