Metadata-Version: 2.1
Name: arikaim-client
Version: 1.0.8
Summary: Arikaim CMS api client
Home-page: https://github.com/arikaim/api-client-py
Download-URL: 
Author: Intersoft Ltd
Author-email: info@arikaim.com
License: MIT License
Keywords: arikaim,arikaim cms,api client
Classifier: Programming Language :: Python :: 3
Classifier: License :: OSI Approved :: MIT License
Classifier: Operating System :: OS Independent
License-File: LICENSE.txt
